AUTHORS.rst
CONTRIBUTING.rst
HISTORY.rst
LICENSE
MANIFEST.in
README.md
setup.cfg
setup.py
docs/Makefile
docs/authors.rst
docs/conf.py
docs/contributing.rst
docs/history.rst
docs/index.rst
docs/installation.rst
docs/make.bat
docs/usage.rst
pip_stripper/__init__.py
pip_stripper/__main__.py
pip_stripper/_baseutils.py
pip_stripper/_pip_stripper.py
pip_stripper/builder.py
pip_stripper/common.py
pip_stripper/matching.py
pip_stripper/pip.py
pip_stripper/trackimports.py
pip_stripper/writers.py
pip_stripper/yaml_commenter.py
pip_stripper.egg-info/PKG-INFO
pip_stripper.egg-info/SOURCES.txt
pip_stripper.egg-info/dependency_links.txt
pip_stripper.egg-info/entry_points.txt
pip_stripper.egg-info/not-zip-safe
pip_stripper.egg-info/requires.txt
pip_stripper.egg-info/top_level.txt
pip_stripper/templates/pip-stripper.yaml
pip_stripper/templates/yaml_comments.yaml
sample/yaml_comments.yaml
sample/tst.init/pip-stripper.yaml
sample/tst.seedworkdir01/py/dummy/__init__.py
sample/tst.seedworkdir01/py/dummy/script01.py
sample/tst.seedworkdir01/py/dummy/script02.py
sample/tst.seedworkdir01/py/tests/test_script01.py
sample/tst.seedworkdir01/py/tests/__pycache__/test_script01.cpython-36-PYTEST.pyc
sample/tst.seedworkdir01/py/tests/__pycache__/test_script01.cpython-37-PYTEST.pyc
tests/__init__.py
tests/test_pip_stripper.py