Metadata-Version: 2.1
Name: pip-stripper
Version: 0.3.0
Summary: strip out unnecessary pip packages from requirements
Home-page: https://github.com/jpeyret/pip-stripper
Author: JL Peyret
Author-email: jpeyret@gmail.com
License: MIT license
Keywords: pip_stripper
Platform: UNKNOWN
Classifier: Development Status :: 2 - Pre-Alpha
Classifier: Intended Audience :: Developers
Classifier: License :: OSI Approved :: MIT License
Classifier: Natural Language :: English
Classifier: Programming Language :: Python :: 3
Classifier: Programming Language :: Python :: 3.4
Classifier: Programming Language :: Python :: 3.5
Classifier: Programming Language :: Python :: 3.6
Classifier: Programming Language :: Python :: 3.7
